ubercode/__init__.py
ubercode/utils/__init__.py
ubercode/utils/convert.py
ubercode/utils/cursor.py
ubercode/utils/data.py
ubercode/utils/dataframe.py
ubercode/utils/environment.py
ubercode/utils/logging.py
ubercode/utils/urls.py
python_ubercode_utils-2.0.3.dist-info/LICENSE
python_ubercode_utils-2.0.3.dist-info/METADATA
python_ubercode_utils-2.0.3.dist-info/WHEEL
python_ubercode_utils-2.0.3.dist-info/top_level.txt
python_ubercode_utils-2.0.3.dist-info/RECORD
