Metadata-Version: 2.1
Name: python-ubercode-utils
Version: 2.0.3
Summary: Core python utilities for all apps
Home-page: https://github.com/sstacha/python-ubercode-utils
Author: Steve Stacha
Author-email: sstacha@gmail.com
License: MIT
Classifier: Development Status :: 3 - Alpha
Classifier: Programming Language :: Python :: 3
Classifier: License :: OSI Approved :: MIT License
Classifier: Operating System :: OS Independent
Classifier: Topic :: Utilities
Requires-Python: >=3.8
License-File: LICENSE
